oremda/api/__init__.py
oremda/api/operator.py
oremda_api-0.0.3.dist-info/WHEEL
oremda_api-0.0.3.dist-info/METADATA
oremda_api-0.0.3.dist-info/RECORD
